Workbook

Sheet 変更履歴
A1: KennerRepository | I1: KL仓库管理系统 表设计 | BC1: 作成日 | BF1: 42451 | BK1: 作成者 | BN1: FNST)周 | BS1: 版数 | BU1: 0.1.00
BC2: 更新日 | BF2: 42451 | BK2: 更新者 | BN2: FNST)周
A4: 変更履历
A5: No | B5: 版数 | D5: 日付 | I5: 変更者 | N5: 内容
A6: 1 | B6: 0.1.00 | D6: 42451 | I6: FNST)周 | N6: 初版
A7: 2
A8: 3
A9: 4
A10: 5
A11: 6
A12: 7
A13: 8
A14: 9
A15: 10
A16: 11
A17: 12
A18: 13
... A32: 27

Sheet 目录
A1: KennerRepository | I1: KL仓库管理系统 表设计 | AD1: 作成日 | AG1: 42451 | AL1: 作成者 | AO1: FNST)周 | AT1: 版数 | AV1: 0.1.00
AD2: 更新日 | AG2: 42451 | AL2: 更新者 | AO2: FNST)周
A4: 目录
A5: No | B5: 表名 | I5: 表记号 | P5: 备注
A6: 1 | B6: 产品表 | I6: product
A7: 2 | B7: 用户表 | I7: user
A8: 3 | B8: 供应商表 | I8: provision
A9: 4 | B9: 应收账款表 | I9: accounts_in
A10: 5 | B10: 应付账款表 | I10: accounts_out
A11: 6 | B11: 入库单表 | I11: storage_in
A12: 7 | B12: 销售单表 | I12: sale
A13: 8 | B13: 调拨单表 | I13: requisition
A14: 9 | B14: 客户表 | I14: customer
A15: 10 | B15: 仓库表 | I15: storage
A16: 11 | B16: 库位表 | I16: locator
A17: 12 | B17: 货位表 | I17: goods_allocation
... A20: 15 | B20: 退换货表 | I20: return_goods

Sheet product
A1: 用户接口设计书 | H1: 表设计 | O1: KennerRepository | AR1: 作成日 | AU1: 2016/3/22 | AY1: 作成者 | BB1: FNST)周 | BG1: 版数 | BI1: =変更履歴!BU1 -> 0.1.00
AR2: 更新日 | AU2: 2016/3/22 | AY2: 更新者 | BB2: FNST)周
A4: 表名 | H4: 产品表 | T4: 表记号 | AA4: product | AU4: Scheme | BB4: KennerRepository
A6: 数据件数 | H6: 0 | P6: 件 | T6: 表机能
A7: 数据大小 | H7: 0 | P7: Byte
A8: 表大小 | H8: =H6*H7 -> 0 | P8: Byte
A10: № | B10: 字段名 | J10: 字段名英文 | R10: 属性 | U10: 位数 | V10: Byte数 | W10: 初始值 | AA10: NOT NULL | AD10: PK | AE10: INDEX1～6 | AK10: SEQ | AL10: FK | AR10: 说明
A11: 1 | B11: ID
A12: 2 | B12: 编号 | J12: product_id | R12: INTEGER | AA12: ○ | AD12: 1 | AK12: ○
A13: 3 | B13: 名称 | J13: product_name | R13: VARCHAR | U13: 255 | V13: 255
A14: 4 | B14: 类别 | J14: product_type | R14: VARCHAR | U14: 255 | V14: 255
A15: 5 | B15: 单位 | J15: product_unit | R15: VARCHAR | U15: 255 | V15: 255
A16: 6 | B16: 规格
A17: 7 | B17: 供应商 | J17: provision_id | R17: INTEGER
A18: 8 | B18: 条码 | J18: product_barcode | R18: VARCHAR | U18: 255 | V18: 255
A19: 9 | B19: 平均进价 | J19: product_buy_price | R19: DECIMAL
A20: 10 | B20: 总金额
A21: 11 | B21: 采购周期
A22: 12 | B22: 销售价1 | J22: product_price1 | R22: DECIMAL
A23: 13 | B23: 销售价2 | J23: product_price2 | R23: DECIMAL
A24: 14 | B24: 销售价3 | J24: product_price3 | R24: DECIMAL
A25: 15 | B25: 库存总数 | J25: product_num | R25: INTEGER
A26: 16 | B26: 最小预警值
A27: 17 | B27: 最大预警值
A28: 18 | B28: 参考预警值
A29: 19 | B29: 状态

Sheet user
A1: 用户接口设计书 | H1: 表设计 | O1: KennerRepository | AR1: 作成日 | AU1: 2016/3/22 | AY1: 作成者 | BB1: FNST)周 | BG1: 版数 | BI1: =変更履歴!BU1 -> 0.1.00
AR2: 更新日 | AU2: 2016/3/22 | AY2: 更新者 | BB2: FNST)周
A4: 表名 | H4: 用户表 | T4: 表记号 | AA4: user | AU4: Scheme | BB4: KennerRepository
A6: 数据件数 | H6: 0 | P6: 件 | T6: 表机能
A7: 数据大小 | H7: 0 | P7: Byte
A8: 表大小 | H8: =H6*H7 -> 0 | P8: Byte
A10: № | B10: 字段名 | J10: 字段名英文 | R10: 属性 | U10: 位数 | V10: Byte数 | W10: 初始值 | AA10: NOT NULL | AD10: PK | AE10: INDEX1～6 | AK10: SEQ | AL10: FK | AR10: 说明
A11: 1 | B11: 工号 | J11: user_id | R11: INTEGER | AA11: ○ | AD11: 1 | AK11: ○
A12: 2 | B12: 名称 | J12: user_name | R12: VARCHAR | U12: 255 | V12: 255
A13: 3 | B13: 部门 | J13: user_department | R13: VARCHAR | U13: 255 | V13: 255
A14: 4 | B14: 电话 | J14: user_tel | R14: VARCHAR | U14: 255 | V14: 255
A15: 5 | B15: 手机 | J15: user_cellphone | R15: VARCHAR | U15: 255 | V15: 255
A16: 6 | B16: 住址 | J16: user_address | R16: VARCHAR | U16: 255 | V16: 255
A17: 8 | B17: 电子邮件 | J17: user_email | R17: VARCHAR | U17: 255 | V17: 255
A18: 9 | B18: 职务 | J18: user_role | R18: VARCHAR | U18: 255 | V18: 255
A19: 10 | B19: 生日 | J19: user_birthday | R19: TIMESTAMP
A20: 11 | B20: 性别 | J20: user_sex | R20: VARCHAR | U20: 255 | V20: 255
A21: 12

Sheet provision
A1: 用户接口设计书 | H1: 表设计 | O1: KennerRepository | AR1: 作成日 | AU1: 2016/3/22 | AY1: 作成者 | BB1: FNST)周 | BG1: 版数 | BI1: =変更履歴!BU1 -> 0.1.00
AR2: 更新日 | AU2: 2016/3/22 | AY2: 更新者 | BB2: FNST)周
A4: 表名 | H4: 供应商表 | T4: 表记号 | AA4: provision | AU4: Scheme | BB4: KennerRepository
A6: 数据件数 | H6: 0 | P6: 件 | T6: 表机能
A7: 数据大小 | H7: 0 | P7: Byte
A8: 表大小 | H8: =H6*H7 -> 0 | P8: Byte
A10: № | B10: 字段名 | J10: 字段名英文 | R10: 属性 | U10: 位数 | V10: Byte数 | W10: 初始值 | AA10: NOT NULL | AD10: PK | AE10: INDEX1～6 | AK10: SEQ | AL10: FK | AR10: 说明
A11: 1 | B11: ID
A12: 2 | B12: 编号 | J12: provision_id | R12: INTEGER | AA12: ○ | AD12: 1 | AK12: ○
A13: 3 | B13: 名称 | J13: provision_name | R13: VARCHAR | U13: 255 | V13: 255
A14: 4 | B14: 电话 | J14: provision_tel | R14: VARCHAR | U14: 255 | V14: 255
A15: 5 | B15: 传真 | J15: provision_fax | R15: VARCHAR | U15: 255 | V15: 255
A16: 6 | B16: 联系人 | J16: provision_contact | R16: VARCHAR | U16: 255 | V16: 255
A17: 7 | B17: 联系人电话 | J17: provision_cellphone | R17: VARCHAR | U17: 255 | V17: 255
A18: 8 | B18: 地址 | J18: provision_address | R18: VARCHAR | U18: 255 | V18: 255
A19: 9 | B19: 备注 | J19: provision_remark | R19: TEXT
A20: 10 | B20: 电子邮件 | J20: provision_email | R20: VARCHAR | U20: 255 | V20: 255
A21: 11 | B21: 网址 | J21: provision_net_address | R21: VARCHAR | U21: 255 | V21: 255
A22: 12 | B22: 状态
A23: 13
A24: 14
A25: 15
A26: 16
A27: 17

Sheet accounts_in
A1: 用户接口设计书 | H1: 表设计 | O1: KennerRepository | AR1: 作成日 | AU1: 2016/3/22 | AY1: 作成者 | BB1: FNST)周 | BG1: 版数 | BI1: =変更履歴!BU1 -> 0.1.00
AR2: 更新日 | AU2: 2016/3/22 | AY2: 更新者 | BB2: FNST)周
A4: 表名 | H4: 应收账款表 | T4: 表记号 | AA4: accounts_in | AU4: Scheme | BB4: KennerRepository
A6: 数据件数 | H6: 0 | P6: 件 | T6: 表机能
A7: 数据大小 | H7: 0 | P7: Byte
A8: 表大小 | H8: =H6*H7 -> 0 | P8: Byte
A10: № | B10: 字段名 | J10: 字段名英文 | R10: 属性 | U10: 位数 | V10: Byte数 | W10: 初始值 | AA10: NOT NULL | AD10: PK | AE10: INDEX1～6 | AK10: SEQ | AL10: FK | AR10: 说明
A11: 2 | B11: 收款单号 | J11: accounts_in_id | R11: INTEGER | AA11: ○ | AD11: 1 | AK11: ○
A12: 3 | B12: 收款日期 | J12: accounts_in_date | R12: TIMESTAMP
A13: 4 | B13: 销售单号 | J13: sale_id | R13: INTEGER
A14: 5 | B14: 应收金额
A15: 6 | B15: 实收金额
A16: 7 | B16: 收款人 | J16: accounts_in_chamberlain | R16: VARCHAR | U16: 255 | V16: 255
A17: 8 | B17: 审批人
A18: 9
A19: 10
A20: 11
A21: 12
A22: 13
A23: 14
A24: 15
A25: 16

Sheet accounts_out
A1: 用户接口设计书 | H1: 表设计 | O1: KennerRepository | AR1: 作成日 | AU1: 2016/3/22 | AY1: 作成者 | BB1: FNST)周 | BG1: 版数 | BI1: =変更履歴!BU1 -> 0.1.00
AR2: 更新日 | AU2: 2016/3/22 | AY2: 更新者 | BB2: FNST)周
A4: 表名 | H4: 应付账款表 | T4: 表记号 | AA4: accounts_out | AU4: Scheme | BB4: KennerRepository
A6: 数据件数 | H6: 0 | P6: 件 | T6: 表机能
A7: 数据大小 | H7: 0 | P7: Byte
A8: 表大小 | H8: =H6*H7 -> 0 | P8: Byte
A10: № | B10: 字段名 | J10: 字段名英文 | R10: 属性 | U10: 位数 | V10: Byte数 | W10: 初始值 | AA10: NOT NULL | AD10: PK | AE10: INDEX1～6 | AK10: SEQ | AL10: FK | AR10: 说明
A11: 1 | B11: 付款单号 | J11: accounts_out_id | R11: INTEGER | AA11: ○ | AD11: 1 | AK11: ○
A12: 2 | B12: 付款日期 | J12: accounts_out_date | R12: TIMESTAMP
A13: 8 | B13: 付款对象 | J13: accounts_out_pay | R13: VARCHAR | U13: 255 | V13: 255
B14: 付款方式 | AR14: 货到付款，预付款
A15: 5 | B15: 采购单号 | R15: INTEGER
B16: 应付金额
B17: 实付金额
A18: 10 | B18: 付款人
A19: 11 | B19: 审批人
A20: 12
A21: 13
A22: 14
A23: 15
A24: 16

Sheet storage_in
A1: 用户接口设计书 | H1: 表设计 | O1: KennerRepository | AR1: 作成日 | AU1: 2016/3/22 | AY1: 作成者 | BB1: FNST)周 | BG1: 版数 | BI1: =変更履歴!BU1 -> 0.1.00
AR2: 更新日 | AU2: 2016/3/22 | AY2: 更新者 | BB2: FNST)周
A4: 表名 | H4: 入库单表 | T4: 表记号 | AA4: storage_in | AU4: Scheme | BB4: KennerRepository
A6: 数据件数 | H6: 0 | P6: 件 | T6: 表机能
A7: 数据大小 | H7: 0 | P7: Byte
A8: 表大小 | H8: =H6*H7 -> 0 | P8: Byte
A10: № | B10: 字段名 | J10: 字段名英文 | R10: 属性 | U10: 位数 | V10: Byte数 | W10: 初始值 | AA10: NOT NULL | AD10: PK | AE10: INDEX1～6 | AK10: SEQ | AL10: FK | AR10: 说明
A11: 2 | B11: 入库单号 | J11: receipt_id | R11: INTEGER | AA11: ○ | AD11: 1 | AK11: ○
A12: 3 | B12: 采购单号
A13: 4 | B13: 入库日期 | J13: receipt_time | R13: TIMESTAMP | W13: CURRENT_TIMESTAMP | AA13: ○
A14: 5 | B14: 供应商
A15: 6 | B15: 货位
A16: 7 | B16: 产品名称 | J16: product_name | R16: VARCHAR | U16: 255 | V16: 255
A17: 8 | B17: 产品编号
A18: 9 | B18: 单位 | J18: product_unit | R18: VARCHAR | U18: 255 | V18: 255
A19: 10 | B19: 数量 | J19: receipt_num | R19: INTEGER
A20: 11 | B20: 单价 | J20: product_sale_price | R20: DECIMAL
A21: 12 | B21: 总金额 | J21: receipt_total_price | R21: DECIMAL
A22: 13
A23: 14
A24: 15
A25: 16
A26: 17
A27: 18
A28: 19
A29: 20

Sheet sale
A1: 用户接口设计书 | H1: 表设计 | O1: KennerRepository | AR1: 作成日 | AU1: 2016/3/22 | AY1: 作成者 | BB1: FNST)周 | BG1: 版数 | BI1: =変更履歴!BU1 -> 0.1.00
AR2: 更新日 | AU2: 2016/3/22 | AY2: 更新者 | BB2: FNST)周
A4: 表名 | H4: 出库单表 | T4: 表记号 | AA4: sale | AU4: Scheme | BB4: KennerRepository
A6: 数据件数 | H6: 0 | P6: 件 | T6: 表机能
A7: 数据大小 | H7: 0 | P7: Byte
A8: 表大小 | H8: =H6*H7 -> 0 | P8: Byte
A10: № | B10: 字段名 | J10: 字段名英文 | R10: 属性 | U10: 位数 | V10: Byte数 | W10: 初始值 | AA10: NOT NULL | AD10: PK | AE10: INDEX1～6 | AK10: SEQ | AL10: FK | AR10: 说明
A11: 2 | B11: 出库单号 | J11: sale_id | R11: INTEGER | AA11: ○ | AD11: 1 | AK11: ○
A12: 3 | B12: 产品名称 | J12: product_name | R12: VARCHAR | U12: 255 | V12: 255
A13: 4 | B13: 产品编号
A14: 5 | B14: 供应商
A15: 6 | B15: 货位
A16: 7 | B16: 出库日期 | J16: sale_time | R16: TIMESTAMP | W16: CURRENT_TIMESTAMP | AA16: ○
A17: 8 | B17: 单位 | J17: product_unit | R17: VARCHAR | U17: 255 | V17: 255
A18: 9 | B18: 数量 | J18: sale_no | R18: INTEGER
A19: 10 | B19: 单价 | J19: product_buy_price | R19: DECIMAL
A20: 11 | B20: 总金额 | J20: sale_total_price | R20: DECIMAL
A21: 12
A22: 13
A23: 14
A24: 15
A25: 16
A26: 17
A27: 18
A28: 19

Sheet requisition
A1: 用户接口设计书 | H1: 表设计 | O1: KennerRepository | AR1: 作成日 | AU1: 2016/3/22 | AY1: 作成者 | BB1: FNST)周 | BG1: 版数 | BI1: =変更履歴!BU1 -> 0.1.00
AR2: 更新日 | AU2: 2016/3/22 | AY2: 更新者 | BB2: FNST)周
A4: 表名 | H4: 调拨单表 | T4: 表记号 | AA4: requisition | AU4: Scheme | BB4: KennerRepository
A6: 数据件数 | H6: 0 | P6: 件 | T6: 表机能
A7: 数据大小 | H7: 0 | P7: Byte
A8: 表大小 | H8: =H6*H7 -> 0 | P8: Byte
A10: № | B10: 字段名 | J10: 字段名英文 | R10: 属性 | U10: 位数 | V10: Byte数 | W10: 初始值 | AA10: NOT NULL | AD10: PK | AE10: INDEX1～6 | AK10: SEQ | AL10: FK | AR10: 说明
A11: 1 | B11: ID
A12: 9 | B12: 调拨日期 | J12: requisition_time | R12: TIMESTAMP | W12: CURRENT_TIMESTAMP | AA12: ○
A13: 1 | B13: 产品编号 | J13: requisition_id | R13: INTEGER | AA13: ○ | AD13: 1 | AK13: ○
A14: 2 | B14: 产品名称 | J14: product_name | R14: VARCHAR | U14: 255 | V14: 255
B15: 调拨单编号
B16: 调出货位
B17: 调入货位
B18: 操作人
A19: 6 | B19: 数量 | J19: requisition_no | R19: INTEGER
A20: 7 | B20: 单价 | J20: product_buy_price | R20: DECIMAL
A21: 8 | B21: 总金额 | J21: requisition_total_price | R21: DECIMAL
A22: 10 | B22: 备注
A23: 11 | B23: 状态
A24: 12
A25: 13
A26: 14
A27: 15
A28: 16
A29: 17

Sheet customer
A1: 用户接口设计书 | H1: 表设计 | O1: KennerRepository | AR1: 作成日 | AU1: 2016/3/22 | AY1: 作成者 | BB1: FNST)周 | BG1: 版数 | BI1: =変更履歴!BU1 -> 0.1.00
AR2: 更新日 | AU2: 2016/3/22 | AY2: 更新者 | BB2: FNST)周
A4: 表名 | H4: 客户表 | T4: 表记号 | AA4: customer | AU4: Scheme | BB4: KennerRepository
A6: 数据件数 | H6: 0 | P6: 件 | T6: 表机能
A7: 数据大小 | H7: 0 | P7: Byte
A8: 表大小 | H8: =H6*H7 -> 0 | P8: Byte
A10: № | B10: 字段名 | J10: 字段名英文 | R10: 属性 | U10: 位数 | V10: Byte数 | W10: 初始值 | AA10: NOT NULL | AD10: PK | AE10: INDEX1～6 | AK10: SEQ | AL10: FK | AR10: 说明
A11: 1 | B11: ID
A12: 2 | B12: 名称 | J12: customer_name | R12: VARCHAR | U12: 255 | V12: 255
A13: 3 | B13: 性别
A14: 4 | B14: 手机号 | J14: customer_cellphone | R14: VARCHAR | U14: 255 | V14: 255
A15: 5 | B15: 地址 | J15: customer_address | R15: VARCHAR | U15: 255 | V15: 255
A16: 6 | B16: 合同号 | J16: customer_remark | R16: TEXT
A17: 7 | B17: 电子邮件 | J17: customer_email | R17: VARCHAR | U17: 255 | V17: 255
A18: 8 | B18: 生日
A19: 9 | B19: 微信/微博
A20: 10
A21: 11
A22: 12
A23: 13

Sheet storage
A1: 用户接口设计书 | H1: 表设计 | O1: KennerRepository | AR1: 作成日 | AU1: 2016/3/22 | AY1: 作成者 | BB1: FNST)周 | BG1: 版数 | BI1: =変更履歴!BU1 -> 0.1.00
AR2: 更新日 | AU2: 2016/3/22 | AY2: 更新者 | BB2: FNST)周
A4: 表名 | H4: 仓库表 | T4: 表记号 | AA4: storage | AU4: Scheme | BB4: KennerRepository
A6: 数据件数 | H6: 0 | P6: 件 | T6: 表机能
A7: 数据大小 | H7: 0 | P7: Byte
A8: 表大小 | H8: =H6*H7 -> 0 | P8: Byte
A10: № | B10: 字段名 | J10: 字段名英文 | R10: 属性 | U10: 位数 | V10: Byte数 | W10: 初始值 | AA10: NOT NULL | AD10: PK | AE10: INDEX1～6 | AK10: SEQ | AL10: FK | AR10: 说明
A11: 1 | B11: ID
A12: 2 | B12: 编号 | J12: storage_id | R12: INTEGER | AA12: ○ | AD12: 1 | AK12: ○
A13: 3 | B13: 仓库名称 | J13: storage_name | R13: VARCHAR | U13: 255 | V13: 255
A14: 4 | B14: 仓库地址 | J14: storage_address | R14: VARCHAR | U14: 255 | V14: 255
A15: 5 | B15: 仓库负责人 | J15: storage_admin | R15: VARCHAR | U15: 255 | V15: 255
A16: 6 | B16: 仓库联系电话 | J16: storage_tel | R16: VARCHAR | U16: 255 | V16: 255
A17: 7 | B17: 上级仓库
A18: 8 | B18: 状态
A19: 9
A20: 10
A21: 11
A22: 12
A23: 13
A24: 14
A25: 15

Sheet locator
A1: 用户接口设计书 | H1: 表设计 | O1: KennerRepository | AR1: 作成日 | AU1: 2016/3/22 | AY1: 作成者 | BB1: FNST)周 | BG1: 版数 | BI1: =変更履歴!BU1 -> 0.1.00
AR2: 更新日 | AU2: 2016/3/22 | AY2: 更新者 | BB2: FNST)周
A4: 表名 | H4: 库位表 | T4: 表记号 | AA4: locator | AU4: Scheme | BB4: KennerRepository
A6: 数据件数 | H6: 0 | P6: 件 | T6: 表机能
A7: 数据大小 | H7: 0 | P7: Byte
A8: 表大小 | H8: =H6*H7 -> 0 | P8: Byte
A10: № | B10: 字段名 | J10: 字段名英文 | R10: 属性 | U10: 位数 | V10: Byte数 | W10: 初始值 | AA10: NOT NULL | AD10: PK | AE10: INDEX1～6 | AK10: SEQ | AL10: FK | AR10: 说明
A11: 1 | B11: ID
A12: 2 | B12: 编号
A13: 3 | B13: 名称
A14: 4 | B14: 所属仓库
A15: 5 | B15: 状态
A16: 6
A17: 7
A18: 8
A19: 9
A20: 10
A21: 11
A22: 12
A23: 13
A24: 14
A25: 15

Sheet goods_allocation
A1: 用户接口设计书 | H1: 表设计 | O1: KennerRepository | AR1: 作成日 | AU1: 2016/3/22 | AY1: 作成者 | BB1: FNST)周 | BG1: 版数 | BI1: =変更履歴!BU1 -> 0.1.00
AR2: 更新日 | AU2: 2016/3/22 | AY2: 更新者 | BB2: FNST)周
A4: 表名 | H4: 货位表 | T4: 表记号 | AA4: goods_allocation | AU4: Scheme | BB4: KennerRepository
A6: 数据件数 | H6: 0 | P6: 件 | T6: 表机能
A7: 数据大小 | H7: 0 | P7: Byte
A8: 表大小 | H8: =H6*H7 -> 0 | P8: Byte
A10: № | B10: 字段名 | J10: 字段名英文 | R10: 属性 | U10: 位数 | V10: Byte数 | W10: 初始值 | AA10: NOT NULL | AD10: PK | AE10: INDEX1～6 | AK10: SEQ | AL10: FK | AR10: 说明
A11: 1 | B11: ID
A12: 2 | B12: 编号
A13: 3 | B13: 名称
A14: 4 | B14: 所属库位
A15: 5 | B15: 状态
A16: 6
A17: 7
A18: 8
A19: 9
A20: 10
A21: 11
A22: 12
A23: 13
A24: 14
A25: 15

Sheet quality_checking
A1: 用户接口设计书 | H1: 表设计 | O1: KennerRepository | AR1: 作成日 | AU1: 2016/3/22 | AY1: 作成者 | BB1: FNST)周 | BG1: 版数 | BI1: =変更履歴!BU1 -> 0.1.00
AR2: 更新日 | AU2: 2016/3/22 | AY2: 更新者 | BB2: FNST)周
A4: 表名 | H4: 质检表 | T4: 表记号 | AA4: quality_checking | AU4: Scheme | BB4: KennerRepository
A6: 数据件数 | H6: 0 | P6: 件 | T6: 表机能
A7: 数据大小 | H7: 0 | P7: Byte
A8: 表大小 | H8: =H6*H7 -> 0 | P8: Byte
A10: № | B10: 字段名 | J10: 字段名英文 | R10: 属性 | U10: 位数 | V10: Byte数 | W10: 初始值 | AA10: NOT NULL | AD10: PK | AE10: INDEX1～6 | AK10: SEQ | AL10: FK | AR10: 说明
A11: 1 | B11: ID
A12: 2 | B12: 质检单号
A13: 3 | B13: 产品编号
A14: 4 | B14: 产品名称
A15: 5 | B15: 质检结果
A16: 6 | B16: 质检结论
A17: 7 | B17: 质检人
A18: 8 | B18: 质检时间
A19: 9
A20: 10
A21: 11
A22: 12
A23: 13
A24: 14
A25: 15

Sheet purchase
A1: 用户接口设计书 | H1: 表设计 | O1: KennerRepository | AR1: 作成日 | AU1: 2016/3/22 | AY1: 作成者 | BB1: FNST)周 | BG1: 版数 | BI1: =変更履歴!BU1 -> 0.1.00
AR2: 更新日 | AU2: 2016/3/22 | AY2: 更新者 | BB2: FNST)周
A4: 表名 | H4: 采购表 | T4: 表记号 | AA4: purchase | AU4: Scheme | BB4: KennerRepository
A6: 数据件数 | H6: 0 | P6: 件 | T6: 表机能
A7: 数据大小 | H7: 0 | P7: Byte
A8: 表大小 | H8: =H6*H7 -> 0 | P8: Byte
A10: № | B10: 字段名 | J10: 字段名英文 | R10: 属性 | U10: 位数 | V10: Byte数 | W10: 初始值 | AA10: NOT NULL | AD10: PK | AE10: INDEX1～6 | AK10: SEQ | AL10: FK | AR10: 说明
A11: 2 | B11: 采购单号
A12: 3 | B12: 接单日期
A13: 4 | B13: 订货日期
A14: 5 | B14: 结款方式
A15: 6 | B15: 含税否
A16: 7 | B16: 订货人
A17: 8 | B17: 供应商
A18: 9 | B18: 订货名称
A19: 10 | B19: 数量
A20: 11 | B20: 单价
A21: 12 | B21: 应付款
A22: 13 | B22: 预计到货日期
... A28: 19 | B28: 运费占比
A29: 20
A30: 21
A31: 22
A32: 23
A33: 24
A34: 25
A35: 26
A36: 27
A37: 28
A38: 29

Sheet return_goods
A1: 用户接口设计书 | H1: 表设计 | O1: KennerRepository | AR1: 作成日 | AU1: 2016/3/22 | AY1: 作成者 | BB1: FNST)周 | BG1: 版数 | BI1: =変更履歴!BU1 -> 0.1.00
AR2: 更新日 | AU2: 2016/3/22 | AY2: 更新者 | BB2: FNST)周
A4: 表名 | H4: 退换货表 | T4: 表记号 | AA4: return_goods | AU4: Scheme | BB4: KennerRepository
A6: 数据件数 | H6: 0 | P6: 件 | T6: 表机能
A7: 数据大小 | H7: 0 | P7: Byte
A8: 表大小 | H8: =H6*H7 -> 0 | P8: Byte
A10: № | B10: 字段名 | J10: 字段名英文 | R10: 属性 | U10: 位数 | V10: Byte数 | W10: 初始值 | AA10: NOT NULL | AD10: PK | AE10: INDEX1～6 | AK10: SEQ | AL10: FK | AR10: 说明
A11: 2 | B11: 退换单号
A12: 3 | B12: 产品名称
A13: 4 | B13: 产品编码
A14: 5 | B14: 供应商
A15: 6 | B15: 合同号
A16: 7 | B16: 状态
A17: 8 | B17: 退换原因
A18: 9
A19: 10
A20: 11
A21: 12
A22: 13
A23: 14
A24: 15
